{
  "worKdol": {
    "description": "",
    "logo": "https://raw.githubusercontent.com/mizzhere/mizzhere.github.io/main/app/imgsubdata/1770567524826_mojio.png",
    "covers": [
      "https://raw.githubusercontent.com/mizzhere/mizzhere.github.io/main/app/imgsubdata/1770567585415_lfi17.png"
    ]
  },
  "SELF-ON KODE": {
    "description": "",
    "logo": "https://raw.githubusercontent.com/mizzhere/mizzhere.github.io/main/app/imgsubdata/1770571346832_4m0hw.png",
    "covers": []
  },
  "Psick Show": {
    "description": "",
    "logo": "https://raw.githubusercontent.com/mizzhere/mizzhere.github.io/main/app/imgsubdata/1770629165216_aua6j.png",
    "covers": [
      "https://raw.githubusercontent.com/mizzhere/mizzhere.github.io/main/app/imgsubdata/1770627775023_rmfyr.png"
    ]
  }
}